omigo_lokki/__init__.py
omigo_lokki-0.9.2.dist-info/METADATA
omigo_lokki-0.9.2.dist-info/WHEEL
omigo_lokki-0.9.2.dist-info/top_level.txt
omigo_lokki-0.9.2.dist-info/RECORD
