Metadata-Version: 2.4
Name: omigo_lokki
Version: 0.9.2
Summary: Data Analytics Library for Python5
Home-page: https://github.com/CrowdStrike/omigo-data-analytics
Author: amit jaiswal
Author-email: amit.jaiswal@gmail.com
Project-URL: Bug Tracker, https://github.com/CrowdStrike/omigo-data-analytics/browse
Classifier: Programming Language :: Python :: 3
Classifier: License :: OSI Approved :: MIT License
Classifier: Operating System :: OS Independent
Requires-Python: >=3.6
Requires-Dist: omigo_core
Requires-Dist: omigo_ext
